{
  "com.winwinzo.goldwinzo.playwinzogold": {
    "localad_url": "",
    "check_livetv_mode": "off",
    "livetv_url": "http://68.183.85.1:8081/live/digi4/playlist.m3u8",
    "qureka_url": "http://725.win.qureka.com/",
    "check_qureka_mode": "off",
    "admob_appid": "",
    "admob_interid": "",
    "admob_bannerid": "",
    "admob_nativebannerid": "",
    "admob_appopenid": "ca-app-pub-3940256099942544/3419835294",
    "fb_interid": "",
    "fb_bannerid": "",
    "fb_native_bannerid": "",
    "fb_nativeid": "",
    "unity_interid": ""
  },
  "com.thopstream.livecricket.thopstv": {
    "localad_url": "https://my-json-server.typicode.com/srbagasariya/localads/moreapps",
    "check_livetv_mode": "on",
    "livetv_url": "http://68.183.85.1:8081/live/digi4/playlist.m3u8",
    "qureka_url": "http://725.win.qureka.com/",
    "check_qureka_mode": "on",
    "admob_appid": "ca-app-pub-3940256099942544~3347511713",
    "admob_interid": "	ca-app-pub-3940256099942544/1033173712",
    "admob_bannerid": "ca-app-pub-3940256099942544/6300978111",
    "admob_nativebannerid": "ca-app-pub-3940256099942544/2247696110",
    "admob_appopenid": "ca-app-pub-3940256099942544/3419835294",
    "fb_interid": "",
    "fb_bannerid": "",
    "fb_native_bannerid": "",
    "fb_nativeid": "",
    "unity_interid": ""
  }
}
